{"chunk_definitions":[{"row":51,"row_count":1,"visible":true,"expansion_state":0,"options":{"engine":"r","message":false,"warning":false,"label":"unnamed-chunk-169"},"document_id":"324FF116","chunk_id":"c3lgsf4nluv9l","chunk_label":"unnamed-chunk-2"},{"row":60,"row_count":1,"visible":true,"expansion_state":0,"options":{"engine":"r","message":false,"warning":false,"label":"unnamed-chunk-170"},"document_id":"324FF116","chunk_id":"cs6i600dseizv","chunk_label":"unnamed-chunk-3"},{"row":72,"row_count":1,"visible":true,"expansion_state":0,"options":{"engine":"r","label":"unnamed-chunk-171"},"document_id":"324FF116","chunk_id":"c0i8hg35o4f6x","chunk_label":"unnamed-chunk-4"},{"row":79,"row_count":1,"visible":true,"expansion_state":0,"options":{"engine":"r","label":"unnamed-chunk-172"},"document_id":"324FF116","chunk_id":"ctz5h1bz4yniy","chunk_label":"unnamed-chunk-5"},{"row":88,"row_count":1,"visible":true,"expansion_state":0,"options":{"engine":"r","label":"unnamed-chunk-173"},"document_id":"324FF116","chunk_id":"cqz0kzkdxi0hj","chunk_label":"unnamed-chunk-6"},{"row":99,"row_count":1,"visible":true,"expansion_state":0,"options":{"engine":"r","collapse":true,"label":"unnamed-chunk-174"},"document_id":"324FF116","chunk_id":"ckvv4rro8q2oz","chunk_label":"unnamed-chunk-7"},{"row":105,"row_count":1,"visible":true,"expansion_state":0,"options":{"engine":"r","label":"unnamed-chunk-175"},"document_id":"324FF116","chunk_id":"c2iri2meyf4ar","chunk_label":"unnamed-chunk-8"},{"row":122,"row_count":1,"visible":true,"expansion_state":0,"options":{"engine":"r","warning":false,"message":false,"label":"unnamed-chunk-176"},"document_id":"324FF116","chunk_id":"cv8w5pkd6k7on","chunk_label":"unnamed-chunk-9"},{"row":152,"row_count":1,"visible":true,"expansion_state":0,"options":{"engine":"r","label":"unnamed-chunk-177"},"document_id":"324FF116","chunk_id":"c7m69hbt1oze2","chunk_label":"unnamed-chunk-10"},{"row":171,"row_count":1,"visible":true,"expansion_state":0,"options":{"engine":"r","label":"unnamed-chunk-178"},"document_id":"324FF116","chunk_id":"cb4uiyhhoarto","chunk_label":"unnamed-chunk-11"},{"row":196,"row_count":1,"visible":true,"expansion_state":0,"options":{"engine":"r","message":false,"label":"unnamed-chunk-179"},"document_id":"324FF116","chunk_id":"csdlsg10gjo9q","chunk_label":"unnamed-chunk-12"},{"row":202,"row_count":1,"visible":true,"expansion_state":0,"options":{"engine":"r","label":"unnamed-chunk-180"},"document_id":"324FF116","chunk_id":"cwz1z090xc2la","chunk_label":"unnamed-chunk-13"},{"row":208,"row_count":1,"visible":true,"expansion_state":0,"options":{"engine":"r","label":"unnamed-chunk-181"},"document_id":"324FF116","chunk_id":"cavglba6eel9o","chunk_label":"unnamed-chunk-14"},{"row":214,"row_count":1,"visible":true,"expansion_state":0,"options":{"engine":"r","label":"unnamed-chunk-191"},"document_id":"324FF116","chunk_id":"c6j480no53ra5","chunk_label":"unnamed-chunk-15"},{"row":227,"row_count":1,"visible":true,"expansion_state":0,"options":{"engine":"r","label":"unnamed-chunk-183"},"document_id":"324FF116","chunk_id":"crjyjay2h523w","chunk_label":"unnamed-chunk-16"},{"row":233,"row_count":1,"visible":true,"expansion_state":0,"options":{"engine":"r","label":"unnamed-chunk-184"},"document_id":"324FF116","chunk_id":"cwslgons3c8r1","chunk_label":"unnamed-chunk-17"},{"row":244,"row_count":1,"visible":true,"expansion_state":0,"options":{"engine":"r","collapse":true,"label":"unnamed-chunk-185"},"document_id":"324FF116","chunk_id":"c5btqgoaakjrn","chunk_label":"unnamed-chunk-18"},{"row":251,"row_count":1,"visible":true,"expansion_state":0,"options":{"engine":"r","label":"unnamed-chunk-186"},"document_id":"324FF116","chunk_id":"cwb9zac8r6axn","chunk_label":"unnamed-chunk-19"},{"row":272,"row_count":1,"visible":true,"expansion_state":0,"options":{"engine":"r","label":"unnamed-chunk-187"},"document_id":"324FF116","chunk_id":"cogwdkftqkyyl","chunk_label":"unnamed-chunk-20"},{"row":291,"row_count":1,"visible":true,"expansion_state":0,"options":{"engine":"r","label":"unnamed-chunk-188"},"document_id":"324FF116","chunk_id":"ciw4d8nq7m0xg","chunk_label":"unnamed-chunk-21"},{"row":309,"row_count":1,"visible":true,"expansion_state":0,"options":{"engine":"r","label":"unnamed-chunk-193"},"document_id":"324FF116","chunk_id":"cnkj0lqmnrpeo","chunk_label":"unnamed-chunk-22"},{"row":315,"row_count":1,"visible":true,"expansion_state":0,"options":{"engine":"r","label":"unnamed-chunk-196"},"document_id":"324FF116","chunk_id":"coprdquq23197","chunk_label":"unnamed-chunk-23"},{"row":348,"row_count":1,"visible":true,"expansion_state":0,"options":{"engine":"r","message":false,"label":"unnamed-chunk-250"},"document_id":"324FF116","chunk_id":"cdb0057rq4n8t","chunk_label":"unnamed-chunk-25"},{"row":372,"row_count":1,"visible":true,"expansion_state":0,"options":{"engine":"r","message":false,"warning":false,"label":"unnamed-chunk-263"},"document_id":"324FF116","chunk_id":"cg79elhgwfmrt","chunk_label":"unnamed-chunk-26"},{"row":492,"row_count":1,"visible":true,"expansion_state":0,"options":{"engine":"r","collapse":true,"label":"unnamed-chunk-297"},"document_id":"324FF116","chunk_id":"cir7mtuj1krp9","chunk_label":"unnamed-chunk-33"},{"row":501,"row_count":1,"visible":true,"expansion_state":0,"options":{"engine":"r","label":"unnamed-chunk-298"},"document_id":"324FF116","chunk_id":"ctccj6iv7whk4","chunk_label":"unnamed-chunk-34"},{"row":507,"row_count":1,"visible":true,"expansion_state":0,"options":{"engine":"r","label":"unnamed-chunk-299"},"document_id":"324FF116","chunk_id":"cmwrewf5slu10","chunk_label":"unnamed-chunk-35"},{"row":521,"row_count":1,"visible":true,"expansion_state":0,"options":{"engine":"r","collapse":true,"label":"unnamed-chunk-300"},"document_id":"324FF116","chunk_id":"c3kakrj7b9mhn","chunk_label":"unnamed-chunk-36"},{"row":532,"row_count":1,"visible":true,"expansion_state":0,"options":{"engine":"r","label":"unnamed-chunk-301"},"document_id":"324FF116","chunk_id":"cuh6x588zz34a","chunk_label":"unnamed-chunk-37"},{"row":552,"row_count":1,"visible":true,"expansion_state":0,"options":{"engine":"r","warning":false,"fig.height":3,"label":"unnamed-chunk-324"},"document_id":"324FF116","chunk_id":"c51giqrtd8nyq","chunk_label":"unnamed-chunk-38"},{"row":567,"row_count":1,"visible":true,"expansion_state":0,"options":{"engine":"r","label":"unnamed-chunk-325"},"document_id":"324FF116","chunk_id":"cdqhysakaffm7","chunk_label":"unnamed-chunk-39"},{"row":575,"row_count":1,"visible":true,"expansion_state":0,"options":{"engine":"r","label":"unnamed-chunk-326"},"document_id":"324FF116","chunk_id":"cu64p1h85zu7o","chunk_label":"unnamed-chunk-40"},{"row":587,"row_count":1,"visible":true,"expansion_state":0,"options":{"engine":"r","label":"unnamed-chunk-337"},"document_id":"324FF116","chunk_id":"c9i3vqul93vyw","chunk_label":"unnamed-chunk-41"},{"row":600,"row_count":1,"visible":true,"expansion_state":0,"options":{"engine":"r","label":"unnamed-chunk-366"},"document_id":"3E47DEAA","chunk_id":"cfy3ediqu25ws","chunk_label":"unnamed-chunk-43"},{"row":630,"row_count":1,"visible":true,"expansion_state":0,"options":{"engine":"r","label":"unnamed-chunk-360"},"document_id":"324FF116","chunk_id":"c0om3uz044he1","chunk_label":"unnamed-chunk-44"},{"row":724,"row_count":1,"visible":true,"expansion_state":0,"options":{"engine":"r","message":false,"warning":false,"label":"unnamed-chunk-362"},"document_id":"324FF116","chunk_id":"cpkqamtr1qd3y","chunk_label":"unnamed-chunk-50"}],"doc_write_time":1690718999,"chunk_rendered_width":400}